LICENSE
MANIFEST.in
readme.md
setup.py
tox.ini
src/username_validator/__init__.py
src/username_validator/username_validator.py
src/username_validator.egg-info/PKG-INFO
src/username_validator.egg-info/SOURCES.txt
src/username_validator.egg-info/dependency_links.txt
src/username_validator.egg-info/requires.txt
src/username_validator.egg-info/top_level.txt