Metadata-Version: 2.1
Name: username-validator
Version: 0.0.1
Summary: Username validation
Home-page: https://github.com/ogrodnek/username_validator
Author: Larry Ogrodnek
Author-email: larry@ogrodnek.com
License: BSD
Platform: UNKNOWN
Classifier: Programming Language :: Python :: 2.7
Classifier: Programming Language :: Python :: 3
Classifier: Programming Language :: Python :: 3.7
Classifier: License :: OSI Approved :: BSD License
